satamanosturi/__init__.py
satamanosturi/__main__.py
satamanosturi/docker.py
satamanosturi/images.py
satamanosturi/models.py
satamanosturi/repos.py
satamanosturi/commands/__init__.py
satamanosturi/commands/copy_image.py
satamanosturi-0.0.1.dist-info/METADATA
satamanosturi-0.0.1.dist-info/WHEEL
satamanosturi-0.0.1.dist-info/entry_points.txt
satamanosturi-0.0.1.dist-info/licenses/LICENSE
satamanosturi-0.0.1.dist-info/RECORD
