Metadata-Version: 2.1
Name: satamanosturi
Version: 0.0.1
Project-URL: Documentation, https://github.com/akx/satamanosturi#readme
Project-URL: Issues, https://github.com/akx/satamanosturi/issues
Project-URL: Source, https://github.com/akx/satamanosturi
Author-email: Aarni Koskela <akx@iki.fi>
License-Expression: MIT
License-File: LICENSE
Classifier: Development Status :: 4 - Beta
Classifier: Programming Language :: Python
Classifier: Programming Language :: Python :: 3.9
Classifier: Programming Language :: Python :: 3.10
Classifier: Programming Language :: Python :: 3.11
Classifier: Programming Language :: Python :: Implementation :: CPython
Classifier: Programming Language :: Python :: Implementation :: PyPy
Requires-Python: >=3.9
Requires-Dist: boto3
Requires-Dist: boto3-stubs[ecr]
Requires-Dist: click
Requires-Dist: docker
